[
    {
        "text": "90 FRAGEN YT-DEUTSCHLAND\n",
        "videoId": "llWe_S5hYVw",
        "time": 0
    },
    {
        "text": "FRAGE 01\nWie heißt der meist abonnierte,\ndeutsche YouTube-Kanal?\n",
        "videoId": "llWe_S5hYVw",
        "time": 60
    },
    {
        "text": "FRAGE 02\nWelcher deutsche Youtube-Kanal\nhat die meisten Video-Views?\n",
        "videoId": "llWe_S5hYVw",
        "time": 120
    },
    {
        "text": "FRAGE 03\nIm Oktober 2012 startete ein Kanal, welcher der erste\n„YouTube-Originalkanal“ in DE war. Wie hieß dieser?\n",
        "videoId": "llWe_S5hYVw",
        "time": 200
    },
    {
        "text": "FRAGE 04\nWer führte 2015 unter dem Hashtag NetzFragtMerkel\nein Interview mit der Bundeskanzlerin?\n",
        "videoId": "llWe_S5hYVw",
        "time": 240
    },
    {
        "text": "FRAGE 05\nUnter welchem Namen ist Kathrin Fricke\nauf YouTube bekannt?\n",
        "videoId": "llWe_S5hYVw",
        "time": 260
    },
    {
        "text": "FRAGE 06\nLaut Kanalinfo besteht das Team PietSmiet aus\n„fünf spieleverrückten ...“?\n",
        "videoId": "llWe_S5hYVw",
        "time": 340
    },
    {
        "text": "FRAGE 07\nNennt die vier YouTuber, die 2015 bei der „TV total\nWok WM“ im Vierer Wok für das Team „World Wide\nWok“ antraten.\n",
        "videoId": "llWe_S5hYVw",
        "time": 360
    },
    {
        "text": "FRAGE 08\nWer hat folgenden Satz auf dem Kanalbanner\nstehen: „Caming, Cringe & Cosplay mit Herz & Hufen“\n",
        "videoId": "llWe_S5hYVw",
        "time": 580
    },
    {
        "text": "FRAGE 09\nOrdne diese YouTube-Kanäle\nnach ihrer Abonnenten-Zahl.\nDhalucard, Reved, Maxim, Kalle\n",
        "videoId": "llWe_S5hYVw",
        "time": 600
    },
    {
        "text": "FRAGE 10\nWelcher deutschsprachige YouTube-Kanal knackte\nals erster die fünf Millionen Abonnenten-Marke?\n",
        "videoId": "llWe_S5hYVw",
        "time": 760
    },
    {
        "text": "FRAGE II\nEin blau-schwarz gestreifter Pullover und eine weiße\nMaske sind das Markenzeichen welches YouTubers?\n",
        "videoId": "llWe_S5hYVw",
        "time": 780
    },
    {
        "text": "FRAGE 12\n„Let's Learn LoL - Shaco Jungle Guide“ ist der Titel\ndes ersten Videos welches YouTubers?\n",
        "videoId": "llWe_S5hYVw",
        "time": 820
    },
    {
        "text": "FRAGE 13\nWie lange brauchten Unge und Co um bei ihrer\nLongboard Tour 2014 von Sylt nach Schloss Neusch-\nwanstein zu gelangen?\n",
        "videoId": "llWe_S5hYVw",
        "time": 840
    },
    {
        "text": "FRAGE 15\nWie heißt der 2006 gegründete Kanal mit dem Sitogan\n„Still making movies since 2004“, der aus weit über 10 Mitgliedern\nbestand und dessen Gründer heute hauptsächlich\nMeerschweinchen-Videos veröffentlicht?\n",
        "videoId": "llWe_S5hYVw",
        "time": 940
    },
    {
        "text": "FRAGE 15\nWie heißt der 2006 gegründete Kanal mit dem Slogan\n„Still making movies since 2004“, der aus weit über 10 Mitgliedern\nbestand und dessen Gründer heute hauptsächlich\nMeerschweinchen-Videos veröffentlicht?\n",
        "videoId": "llWe_S5hYVw",
        "time": 960
    },
    {
        "text": "FRAGE 16\nIn welchem Jahr wurde YouTube gegründet?\n",
        "videoId": "llWe_S5hYVw",
        "time": 1020
    },
    {
        "text": "FRAGE 17\nBevor Julien Bam mit seinem gleichnamigen Kanal\ndurchstartete, betrieb er zusammen mit zwei\nKollegen einen Kurzfilmkanal, der wie hieß?\n",
        "videoId": "llWe_S5hYVw",
        "time": 1060
    },
    {
        "text": "FRAGE 18\nDas Intro welches YouTubers beginnt mit den\nWorten „Es ist schon wieder Montag, hier ist der\nFlashback“\n",
        "videoId": "llWe_S5hYVw",
        "time": 1120
    },
    {
        "text": "FRAGE 19\n2016 startete auf YouTube eine in Wuppertal spielende\nMystery-Webserie in welcher es um eine geheimnisvolle App geht,\nwelche einem jeden Wunsch erfüllt.\nAllerdings nicht ohne Gegenleistung. Wie heißt diese Serie?\n",
        "videoId": "llWe_S5hYVw",
        "time": 1180
    },
    {
        "text": "FRAGE 20\nWie viele Euro kamen bisher bei allen Friendly Fire\nStreams, inklusive des FriendlyDistancing, an Zu-\nschauerspenden zusammen?\n",
        "videoId": "llWe_S5hYVw",
        "time": 1220
    },
    {
        "text": "FRAGE 21\nWelcher berliner YouTuber ist dafür bekannt, dass er oft auf den\nKanälen anderer YouTuber oder auf Gemeinschaftskanälen zu\nsehen war bzw ist, jedoch auf seinem eigenen Kanal so gut wie\nniemals Videos hochgeladen hat?\n",
        "videoId": "llWe_S5hYVw",
        "time": 1400
    },
    {
        "text": "FRAGE 22\nWelche Insel ist momentan das\nAuswanderungsziel vieler YouTuber?\n",
        "videoId": "llWe_S5hYVw",
        "time": 1440
    },
    {
        "text": "FRAGE 23\nWelches YouTuber-Duo, das sich vorwiegend auf Videos\nzu Filmen und Serien spezialisiert, ist auch unter dem\nNamen „Leegendarya Films“ bekannt?\n",
        "videoId": "llWe_S5hYVw",
        "time": 1460
    },
    {
        "text": "FRAGE 24\nWelche beiden YouTuber sind Namensgeber\ndes Kanals „DoktorFroid“?\n",
        "videoId": "llWe_S5hYVw",
        "time": 1500
    },
    {
        "text": "FRAGE 25\nIn welchen Jahren war Gronkh der\nmeist abonnierte Kanal Deutschlands?\n",
        "videoId": "llWe_S5hYVw",
        "time": 1520
    },
    {
        "text": "FRAGE 26\nUnter welchem Namen waren\nAndre, Jan und Cengiz auf YouTube bekannt?\n",
        "videoId": "llWe_S5hYVw",
        "time": 1740
    },
    {
        "text": "FRAGE 27\nFür welches Video gewann Rezo 2019 den\nSpecial Award beim „Coldene Kamera Digital Award“?\n",
        "videoId": "llWe_S5hYVw",
        "time": 1760
    },
    {
        "text": "FRAGE 28\nMilch ist ...?\n",
        "videoId": "llWe_S5hYVw",
        "time": 1800
    },
    {
        "text": "FRAGE 29\nAm 07.03.2021 erfüllte sich Varion einen langen Traum,\nindem er ein Video veröffentlichte, in dem wer einen\nGastauftritt hatte?\n",
        "videoId": "llWe_S5hYVw",
        "time": 1820
    },
    {
        "text": "FRAGE 30\nSeit welchem Jahr gibt es das\nYouTube-Partnerprogramm in Deutschland?\n",
        "videoId": "llWe_S5hYVw",
        "time": 1860
    },
    {
        "text": "FRAGE 31\n2017 startete erstmals das PUBG Turnier „BAAL“.\nFür was ist BAAL die Abkürzung?\n",
        "videoId": "llWe_S5hYVw",
        "time": 1940
    },
    {
        "text": "FRAGE 32\nNenne die sieben Gast-Mitspieler, die 2018 an PietSmiets\nSuper Mario Tennis Aces Allstars Turnier teilnahmen.\n",
        "videoId": "llWe_S5hYVw",
        "time": 2000
    },
    {
        "text": "FRAGE 32\nNenne die sieben GCast-Mitspieler, die 2018 an PietSmiets\nSuper Mario Tennis Aces Allstars Turnier teilnahmen.\n",
        "videoId": "llWe_S5hYVw",
        "time": 2020
    },
    {
        "text": "FRAGE 33\n2016 startete Moondye7 ein Arma 3 Server Event, bei dem\nes storytechnisch um Roleplay in einem bestimmten\nSpiele-Universum ging. In welchem?\n",
        "videoId": "llWe_S5hYVw",
        "time": 2300
    },
    {
        "text": "FRAGE 34\nWelche 10 YouTuber treten in der ersten Staffel der 2014\nstartenden YouTube-Animationsserie „TubeClash“ von\nDarkvictory in zwei Teams gegeneinander an?\n",
        "videoId": "llWe_S5hYVw",
        "time": 2360
    },
    {
        "text": "FRAGE 35\nUnter welchem Namen veröffentlichte Dennis Werth, der\nBruder von Pandorya, früher seine Videos auf YouTube,\nbevor er den Kanal in „Dennis Werth“ umbenannte?\n",
        "videoId": "llWe_S5hYVw",
        "time": 2580
    },
    {
        "text": "FRAGE 36\nWelche vier YouTuber gehörten zum\n„HOWAIZEN SQUAD“ oder auch HWSQ?\n",
        "videoId": "llWe_S5hYVw",
        "time": 2620
    },
    {
        "text": "FRAGE 37\nWelche YouTuber hatten einen Gastauftritt im Spiel\n„Elex“ von Piranha Bytes?\n",
        "videoId": "llWe_S5hYVw",
        "time": 2640
    },
    {
        "text": "FRAGE 38\nIm Jahr 2011 stand ein Lied des Comedy-Trios Y-Titty auf\nPlatz 48 der deutschen Charts. Wie heißt das Lied?\n",
        "videoId": "llWe_S5hYVw",
        "time": 2700
    },
    {
        "text": "FRAGE 39\nWelcher dieser Charaktere ist nicht auf\ndem Kanalbanner von PietSmiet zu sehen?\nJohn Marston (Red Dead Redemption), Joel & Ellie (The Last Of Us),\nAloy (Horizon Zero Dawn), Lara Croft (Tomb Raider), Agent 47 (Hitman)\n",
        "videoId": "llWe_S5hYVw",
        "time": 2760
    },
    {
        "text": "FRAGE 40\nWelcher dieser drei Nominierten gewann 2017\nden Webvideopreis in der Kategorie „GCaming“?\nSturmwaffel, Paluten oder tinNendo\n",
        "videoId": "llWe_S5hYVw",
        "time": 2860
    },
    {
        "text": "FRAGE 41\nWie heißt der Film von freshtorge aus dem Jahr 2015?\n",
        "videoId": "llWe_S5hYVw",
        "time": 2880
    },
    {
        "text": "FRAGE 42\nWelcher YouTuber ist für Formate wie\n„So ein Scheiss!“ oder „Erklärbär“ bekannt?\n",
        "videoId": "llWe_S5hYVw",
        "time": 2920
    },
    {
        "text": "FRAGE 43\nIm Spiel „Crash Bandicoot 4: It's About Time“ liehen\nvier YouTuber den Quantum-Masken ihre Stimme.\nWer sind diese vier?\n",
        "videoId": "llWe_S5hYVw",
        "time": 2960
    },
    {
        "text": "FRAGE 44\nAm 01. März 2013 fand der Stream „Last Man Standing“ statt, in\nwelchem Team PietSmiet gegen das Team von Let's Play Together\nantrat. Für LPT trat damals ein YouTuber an, der in diesem Stream\ndas erste Mal live vor einer Kamera stand. Wer war das?\n",
        "videoId": "llWe_S5hYVw",
        "time": 3060
    },
    {
        "text": "FRAGE 45\nBeim Comedy-Trio Y-Titty gab es einen Running Gag,\nwelcher besagt, dass TC immer wen oder was\nschauspielerte?\n",
        "videoId": "llWe_S5hYVw",
        "time": 3120
    },
    {
        "text": "FRAGE 46\nWo fand „Last Man Standing 3“ oder auch\n„Last Man Standing Generations“ statt?\n",
        "videoId": "llWe_S5hYVw",
        "time": 3140
    },
    {
        "text": "FRAGE 47\nWer startete 2006, als einer der ersten deutschen Let's\nPlayer unter dem Namen „Aligator1024“\nseine YouTube-Karriere?\n",
        "videoId": "llWe_S5hYVw",
        "time": 3180
    },
    {
        "text": "FRAGE 48\nSeit wann gibt es in Deutschland die\n„YouTube Premium“ Funktion?\n",
        "videoId": "llWe_S5hYVw",
        "time": 3200
    },
    {
        "text": "FRAGE 49\nWie viele verschiedene Logos hatte YouTube bisher?\n",
        "videoId": "llWe_S5hYVw",
        "time": 3240
    },
    {
        "text": "FRAGE 50\nWie heißt der Spenden-Stream, welcher jährlich gegen\nEnde des Jahres stattfindet und von LeFloid und Co\nveranstaltet wird?\n",
        "videoId": "llWe_S5hYVw",
        "time": 3280
    }
]